libtorch/__init__.py
libtorch/build-version
libtorch/lib/libc10.so
libtorch/lib/libcaffe2_detectron_ops.so
libtorch/lib/libcaffe2_module_test_dynamic.so
libtorch/lib/libfoxi.so
libtorch/lib/libfoxi_dummy.so
libtorch/lib/libgomp-8bba0e50.so.1
libtorch/lib/libonnxifi.so
libtorch/lib/libonnxifi_dummy.so
libtorch/lib/libtorch.so
libtorch-1.2.0.1.dist-info/METADATA
libtorch-1.2.0.1.dist-info/WHEEL
libtorch-1.2.0.1.dist-info/top_level.txt
libtorch-1.2.0.1.dist-info/RECORD
