Metadata-Version: 2.1
Name: libtorch
Version: 1.2.0.1
Summary: libtorch
Home-page: https://pypi.org/project/libtorch/
Author: anycode
Author-email: anycode@yahoo.com
Maintainer: anycode
Maintainer-email: anycode@yahoo.com
License: UNKNOWN
Platform: all
Classifier: Operating System :: OS Independent
Classifier: Programming Language :: Python
Classifier: Intended Audience :: Developers
Classifier: Topic :: Software Development :: Libraries
